meetup2xibo/__init__.py
meetup2xibo/log_summarizer/__init__.py
meetup2xibo/log_summarizer/__main__.py
meetup2xibo/log_summarizer/application_scope.py
meetup2xibo/log_summarizer/command_line.py
meetup2xibo/log_summarizer/conflict.py
meetup2xibo/log_summarizer/conflict_reporter.py
meetup2xibo/log_summarizer/crud_lister.py
meetup2xibo/log_summarizer/event.py
meetup2xibo/log_summarizer/event_log.py
meetup2xibo/log_summarizer/injector.py
meetup2xibo/log_summarizer/location_mapper.py
meetup2xibo/log_summarizer/log_lines.py
meetup2xibo/log_summarizer/log_parser.py
meetup2xibo/log_summarizer/log_summarizer.py
meetup2xibo/log_summarizer/renderer.py
meetup2xibo/log_summarizer/start_counter.py
meetup2xibo/log_summarizer/suppressed_event_tracker.py
meetup2xibo/log_summarizer/templates/report.html
meetup2xibo/log_summarizer/templates/summary.html
meetup2xibo/updater/__init__.py
meetup2xibo/updater/__main__.py
meetup2xibo/updater/anti_flapper.py
meetup2xibo/updater/application_scope.py
meetup2xibo/updater/careful_environment.py
meetup2xibo/updater/command_line.py
meetup2xibo/updater/conflict_analyzer.py
meetup2xibo/updater/conflict_places.py
meetup2xibo/updater/event_converter.py
meetup2xibo/updater/event_location.py
meetup2xibo/updater/event_suppressor.py
meetup2xibo/updater/event_updater.py
meetup2xibo/updater/exceptions.py
meetup2xibo/updater/http_response_error.py
meetup2xibo/updater/injector.py
meetup2xibo/updater/location_chooser.py
meetup2xibo/updater/logging_application.py
meetup2xibo/updater/logging_context.py
meetup2xibo/updater/logging_setup_manager.py
meetup2xibo/updater/meetup2xibo.py
meetup2xibo/updater/meetup_api.py
meetup2xibo/updater/meetup_id_comparable.py
meetup2xibo/updater/oauth2_session_starter.py
meetup2xibo/updater/phrase_mapper.py
meetup2xibo/updater/place_finder.py
meetup2xibo/updater/places.py
meetup2xibo/updater/scope_cache.py
meetup2xibo/updater/site_cert_assurer.py
meetup2xibo/updater/special_location.py
meetup2xibo-3.3.1.dist-info/AUTHORS.rst
meetup2xibo-3.3.1.dist-info/LICENSE
meetup2xibo-3.3.1.dist-info/METADATA
meetup2xibo-3.3.1.dist-info/WHEEL
meetup2xibo-3.3.1.dist-info/entry_points.txt
meetup2xibo-3.3.1.dist-info/top_level.txt
meetup2xibo-3.3.1.dist-info/RECORD
