Metadata-Version: 2.1
Name: meetup2xibo
Version: 3.3.1
Summary: Load Meetup events into a Xibo digital signage CMS.
Home-page: https://github.com/jshprentz/meetup2xibo
Author: Joel Shprentz
Author-email: jshprentz@his.com
License: MIT license
Project-URL: Source Code, https://github.com/jshprentz/meetup2xibo
Project-URL: Documentation, https://meetup2xibo.readthedocs.io/
Keywords: meetup2xibo
Platform: UNKNOWN
Classifier: Development Status :: 5 - Production/Stable
Classifier: Intended Audience :: System Administrators
Classifier: License :: OSI Approved :: MIT License
Classifier: Natural Language :: English
Classifier: Programming Language :: Python :: 3.5
Classifier: Programming Language :: Python :: 3.6
Classifier: Programming Language :: Python :: 3.7
Classifier: Topic :: Communications
Requires-Dist: requests
Requires-Dist: requests-toolbelt
Requires-Dist: oauthlib
Requires-Dist: jinja2
Requires-Dist: requests-oauthlib
Requires-Dist: pyahocorasick
Requires-Dist: parsley
Requires-Dist: pytz
